pyjdb/__init__.py
pyjdb/version.py
pyjdb/core/__init__.py
pyjdb/core/exceptions.py
pyjdb/core/helpers.py
pyjdb/core/jdb_process.py
pyjdb-0.0.6.dist-info/LICENSE
pyjdb-0.0.6.dist-info/METADATA
pyjdb-0.0.6.dist-info/WHEEL
pyjdb-0.0.6.dist-info/top_level.txt
pyjdb-0.0.6.dist-info/RECORD
